slidedown/__init__.py
slidedown/__main__.py
slidedown/hooks.py
slidedown/slides.py
slidedown/static/markdown.css
slidedown-0.7.0.dist-info/LICENSE
slidedown-0.7.0.dist-info/METADATA
slidedown-0.7.0.dist-info/WHEEL
slidedown-0.7.0.dist-info/entry_points.txt
slidedown-0.7.0.dist-info/top_level.txt
slidedown-0.7.0.dist-info/RECORD
