Metadata-Version: 2.1
Name: slidedown
Version: 0.7.0
Summary: Simple slide decks with Markdown and Python
Home-page: https://github.com/rmorshea/slidedown
Author: Ryan Morshead
Author-email: ryan.morshead@gmail.com
License: MIT
Keywords: slideshow,markdown,idom
Platform: Linux
Platform: Mac OS X
Platform: Windows
Requires-Python: >=3.6,<4.0
Requires-Dist: docopt (==0.6.2)
Requires-Dist: idom[stable] (<0.34,>=0.33.2)
Requires-Dist: pygments (==2.7.4)
Requires-Dist: markdown (==3.3.3)
